LICENSE.txt
MANIFEST.in
README.md
setup.py
maxpytest/__init__.py
maxpytest/__main__.py
maxpytest/callscript_restarter.py
maxpytest/callscript_testcaller.py
maxpytest/callscripts.py
maxpytest/cli.py
maxpytest/maxcom.py
maxpytest/runner.py
maxpytest.egg-info/PKG-INFO
maxpytest.egg-info/SOURCES.txt
maxpytest.egg-info/dependency_links.txt
maxpytest.egg-info/entry_points.txt
maxpytest.egg-info/requires.txt
maxpytest.egg-info/top_level.txt
tests/__init__.py
tests/unit/__init__.py
tests/unit/conftest.py
tests/unit/test_callscripts.py
tests/unit/test_cli.py
tests/unit/test_maxcom.py
tests/unit/test_runner.py
tests/unit/test_testcaller.py